symphonizer/__init__.py
symphonizer/composition.py
symphonizer/instruments/__init__.py
symphonizer/instruments/mock.py
symphonizer/instruments/nuropb_api.py
symphonizer/instruments/rest.py
symphonizer/interface.py
symphonizer/node_runner.py
symphonizer/perform.py
symphonizer/utils.py
symphonizer-0.1.2.dist-info/LICENSE
symphonizer-0.1.2.dist-info/METADATA
symphonizer-0.1.2.dist-info/WHEEL
symphonizer-0.1.2.dist-info/entry_points.txt
symphonizer-0.1.2.dist-info/RECORD
