Metadata-Version: 2.1
Name: symphonizer
Version: 0.1.2
Summary: Orchestrate anything with low overhead, fast, synchronized scheduling.
Home-page: https://github.com/robertbetts/Symphonizer
License: Apache-2.0
Keywords: python,ai,llm,agents,orchestration,process-management,task-management,dag,process-flow
Author: Robert Betts
Author-email: robert.betts@yahoo.com
Requires-Python: >=3.9,<3.12
Classifier: License :: OSI Approved :: Apache Software License
Classifier: Operating System :: OS Independent
Classifier: Programming Language :: Python :: 3
Classifier: Programming Language :: Python :: 3.9
Classifier: Programming Language :: Python :: 3.10
Classifier: Programming Language :: Python :: 3.11
Provides-Extra: integrations
Requires-Dist: aiohttp (>=3.8.5,<4.0.0) ; extra == "integrations"
Requires-Dist: coverage[toml] (>=7.3.1,<8.0.0)
Requires-Dist: nuropb (>=0.1.3,<0.2.0) ; extra == "integrations"
Project-URL: Repository, https://github.com/robertbetts/Symphonizer
